urw_scroll_table/__init__.py
urw_scroll_table/table.py
urw_scroll_table/widgets.py
urw_scroll_table-0.1.2.dist-info/LICENSE
urw_scroll_table-0.1.2.dist-info/METADATA
urw_scroll_table-0.1.2.dist-info/WHEEL
urw_scroll_table-0.1.2.dist-info/RECORD
