Metadata-Version: 2.1
Name: urw-scroll-table
Version: 0.1.2
Summary: A scrollable and editable table widget for urwid terminal applications
Author: Sergey Zhumatiy
Author-email: sergzhum@gmail.com
Requires-Python: >=3.8,<4.0
Classifier: Programming Language :: Python :: 3
Classifier: Programming Language :: Python :: 3.8
Classifier: Programming Language :: Python :: 3.9
Classifier: Programming Language :: Python :: 3.10
Classifier: Programming Language :: Python :: 3.11
Classifier: Programming Language :: Python :: 3.12
Requires-Dist: urwid (>=3.0.0,<4.0.0)
